setup.cfg
setup.py
tokenquery/__init__.py
tokenquery/tokenquery.py
tokenquery.egg-info/PKG-INFO
tokenquery.egg-info/SOURCES.txt
tokenquery.egg-info/dependency_links.txt
tokenquery.egg-info/requires.txt
tokenquery.egg-info/top_level.txt
tokenquery/acceptors/__init__.py
tokenquery/acceptors/core/__init__.py
tokenquery/acceptors/core/date_opr.py
tokenquery/acceptors/core/int_opr.py
tokenquery/acceptors/core/string_opr.py
tokenquery/acceptors/core/vector_opr.py
tokenquery/acceptors/core/web_opr.py
tokenquery/acceptors/extended/__init__.py
tokenquery/acceptors/extended/date.py
tokenquery/acceptors/extended/ner.py
tokenquery/acceptors/extended/pos.py
tokenquery/acceptors/extended/web.py
tokenquery/models/__init__.py
tokenquery/models/chunk.py
tokenquery/models/fsa.py
tokenquery/models/graph.py
tokenquery/models/stack.py
tokenquery/models/token.py
tokenquery/models/tree.py
tokenquery/nlp/__init__.py
tokenquery/nlp/google_nlp_api.py
tokenquery/nlp/importer.py
tokenquery/nlp/pos_tagger.py
tokenquery/nlp/tokenizer.py
tokenquery/tests/__init__.py
tokenquery/tests/tokenquery_test.py