Metadata-Version: 1.1
Name: tokenquery
Version: 0.1.1
Summary: Tokenquery - query language for tokens 
Home-page: https://github.com/ramtinms/tokenquery
Author: Ramtin Seraj
Author-email: mehdizadeh.ramtin@gmail.com
License: UNKNOWN
Download-URL: https://github.com/ramtinms/tokenquery/tarball/0.1
Keywords: natural language processing,nlp,regex,regular expressions,tokenizer,query
Platform: UNKNOWN
Classifier: Intended Audience :: Information Technology
Classifier: Intended Audience :: Science/Research
Classifier: Topic :: Scientific/Engineering
Classifier: Topic :: Scientific/Engineering :: Artificial Intelligence
Classifier: Topic :: Scientific/Engineering :: Human Machine Interfaces
Classifier: Topic :: Scientific/Engineering :: Information Analysis
Classifier: Topic :: Text Processing
Classifier: Topic :: Text Processing :: Filters
Classifier: Topic :: Text Processing :: General
Classifier: Topic :: Text Processing :: Indexing
Classifier: Topic :: Text Processing :: Linguistic
